surquest/utils/qdict/__init__.py
surquest/utils/qdict/attribute.py
surquest/utils/qdict/dataset.py
surquest/utils/qdict/helpers.py
surquest_utils_qdict-0.0.1rc2.dist-info/METADATA
surquest_utils_qdict-0.0.1rc2.dist-info/WHEEL
surquest_utils_qdict-0.0.1rc2.dist-info/licenses/LICENSE
surquest_utils_qdict-0.0.1rc2.dist-info/RECORD
