Metadata-Version: 2.4
Name: surquest-utils-qdict
Version: 0.0.1rc2
Summary: This python package simplifies the manipulation with the lists of multi-dimensional dictionaries as select, filter or join.
Project-URL: Homepage, https://github.com/surquest/python-utils-qdict
Project-URL: Bug Tracker, https://github.com/surquest/python-utils-qdict/issues
Author-email: Michal Švarc <michal.svarc@surquest.com>
License-File: LICENSE
Provides-Extra: test
Requires-Dist: pytest-cov==6.0.0; extra == 'test'
Requires-Dist: pytest==8.3.4; extra == 'test'
